Workbook

Sheet INSTRUCCIONES
B2: PLANTILLA DE CAPTURA v2 — REPORTERIA FINANCIERA Y OPERATIVA
B4: Objetivo | C4: Estandarizar la captura de informacion para generar automaticamente reportes de ventas, utilidad, cobranza, flujo de efectivo y rentabilidad por modelo.
B6: COMO USAR ESTE ARCHIVO
B7: 1 | C7: Capture UNA FILA POR MOVIMIENTO: una por producto vendido, una por pago recibido, una por gasto. No agrupe ni resuma: el sistema hace los totales.
B8: 2 | C8: Solo escriba en las celdas de LETRA AZUL. Las columnas de letra negra de la hoja ventas (utilidad, margen, cobrado y saldo) se calculan solas con formulas: no escriba en ellas. La aplicacion las vuelve a calcular por su cuenta al cargar el archivo.
B9: 3 | C9: Las celdas con FONDO AMARILLO son datos que faltan y son necesarios. Complete lo que pueda.
B10: 4 | C10: La fila con FONDO VERDE de cada hoja es un EJEMPLO. No la borre, sirve de referencia de formato.
B11: 5 | C11: Use las listas desplegables donde existan: evitan errores de dedo (ej. 'Accesorios' vs 'Accesorio' en linea). El modelo es texto libre: el sistema ignora mayusculas y espacios sobrantes al agrupar, pero no une nombres escritos distinto; escribalo siempre igual.
B12: 6 | C12: El folio identifica UNA VENTA. Una venta con varios productos repite su folio en cada fila (vea 'Ventas con varios productos', abajo). Nunca use el mismo folio para dos ventas distintas: es la llave que une las hojas.
B13: 7 | C13: No inserte columnas nuevas ni cambie los encabezados.
B15: LAS 4 HOJAS DE CAPTURA
B16: 1. ventas | C16: Una fila por producto vendido (equipo, accesorio, servicio). Si una venta incluye 2 productos, son 2 filas con el mismo folio.
B17: 2. cobranza | C17: Una fila POR CADA PAGO O ABONO recibido, con su fecha y el folio de la venta que paga. Si un cliente abono 3 veces, son 3 filas. Sin esta hoja no se puede saber cuanto se debe ni desde cuando.
B18: 3. gastos | C18: TODOS los gastos del negocio: nomina, renta, luz, gasolina, viaticos, publicidad, intereses, importacion. Uno por fila, con fecha.
B19: 4. parametros | C19: Configuracion general: moneda, IVA, tasa de provision. Se llena una sola vez. Porcentajes: 30%, 30 y 0.30 valen lo mismo; un numero mayor que 1 se lee como por ciento, y 1 solo es 100% (para uno por ciento escriba 1%). Fechas en dd/mm/aaaa.
B21: REGLAS CRITICAS
B22: Costo | C22: El costo debe ser el COSTO REAL DE ADQUISICION: precio del proveedor + flete + aduana + maniobras. No lo calcule como un porcentaje del precio de venta.
B23: IVA | C23: Defina en 'parametros' si los importes llevan IVA incluido y capture SIEMPRE igual. Mezclar con y sin IVA invalida todos los reportes.
B24: Credito | C24: Registre siempre los DIAS DE CREDITO pactados. Sin ese dato no se puede saber que cuenta esta vencida. Cuentan desde la fecha de entrega de cada producto.
B25: Comision | C25: Indique si el porcentaje se calcula sobre la VENTA o sobre la UTILIDAD. Cambia el resultado en cientos de miles.
B27: CODIGO DE COLOR
B28: Letra azul | C28: Dato que usted captura a mano.
B29: Letra negra | C29: Columna calculada con formula. No escriba en ella.
B30: Fondo amarillo | C30: Dato faltante o pendiente de confirmar.
B31: Fondo verde | C31: Fila de ejemplo.
B33: VENTAS CON VARIOS PRODUCTOS
B34: Mismo folio | C34: Una venta que incluye varios productos se captura en varias filas CON EL MISMO FOLIO, una por producto. Ejemplo: V-101, Equipo, Modelo A, $100,000 y en la fila de abajo V-101, Accesorios, Modelo B, $10,000. Es UNA venta de $110,000 con dos partidas.
B35: Datos de la venta | C35: Cliente, dias de credito, condicion y vendedor son de la venta completa. Al repetir el folio en la fila de abajo se copian solos de la fila de arriba; puede escribir encima si hace falta. Si quedan vacios, la aplicacion toma los de la primera fila de ese folio que los traiga.
B36: Fecha | C36: La fecha es la de ENTREGA de cada producto. Si el equipo se entrego un dia y el accesorio otro, cada fila lleva su fecha. Los dias de credito cuentan desde cada entrega.
B37: Cobrado y saldo | C37: Son de la venta completa y aparecen solo en la PRIMERA fila de cada folio. En las demas filas del mismo folio vera una flecha ↑, que quiere decir 'vea la primera fila de este folio'. Asi la columna se puede sumar sin contar la misma venta dos veces.
B38: Pagos | C38: En la hoja cobranza cada pago se anota contra el FOLIO de la venta, no contra un producto. Se aplican primero a lo que se entrego primero: lo que queda pendiente es lo ultimo entregado.
B39: Linea Demo | C39: Una unidad de linea Demo no es una venta. La hoja si suma en 'cobrado' los pagos anotados contra su folio, pero el reporte no los cuenta como cobranza: por eso el total de esa columna puede ser mayor que el 'Efectivo cobrado' del reporte.

Sheet _listas
A1: Equipo | B1: Contado | C1: Venta | D1: Nomina | E1: Fijo | F1: Efectivo
A2: Accesorios | B2: Credito | C2: Utilidad | D2: Renta | E2: Variable | F2: Transferencia
A3: Refacciones | B3: Consignacion | C3: No aplica | D3: Servicios | F3: Cheque
A4: Servicio | D4: Operativos | F4: Deposito
A5: Capacitacion | D5: Comercial | F5: Otro
A6: Demo | D6: Viaticos
D7: Logistica
D8: Importacion
D9: Financieros
D10: Impuestos
D11: Otros

Sheet ventas
A1: folio | B1: fecha | C1: linea | D1: cliente | E1: modelo | F1: serie | G1: costo_unitario | H1: precio_venta | I1: comision_pct | J1: comision_base | K1: dias_credito | L1: condicion | M1: vendedor | N1: utilidad_bruta | O1: margen_pct | P1: cobrado | Q1: saldo | R1: notas
A2: V-000 | B2: 15/03/2026 | C2: Equipo | D2: EJEMPLO — Cliente Demostrativo | E2: Modelo A | F2: ABC123456789 | G2: 200000 | H2: 260000 | I2: 0.05 | J2: Venta | K2: 90 | L2: Credito | M2: Nombre vendedor | N2: =IFERROR(H2-G2,"") -> 60000 | O2: =IFERROR(N2/H2,"") -> 0.23076923 | P2: =IFERROR(SUMIF(cobranza!$B$3:$B$1000,A2,cobranza!$D$3:$D$1000),0) -> 0 | Q2: =IFERROR(H2-P2,"") -> 260000 | R2: Fila de ejemplo — no borrar
D3: =IF(AND($A3<>"",$A3=$A2),D2,"") | K3: =IF(AND($A3<>"",$A3=$A2),K2,"") | L3: =IF(AND($A3<>"",$A3=$A2),L2,"") | M3: =IF(AND($A3<>"",$A3=$A2),M2,"") | N3: =IF(H3="","",H3-G3) | O3: =IFERROR(N3/H3,"") | P3: =IF($A3="","",IF(COUNTIF($A$3:$A3,$A3)=1,SUMIF(cobranza!$B$3:$B$1000,$A3,cobranza!$D$3:$D$1000),"↑")) | Q3: =IF($A3="","",IF(COUNTIF($A$3:$A3,$A3)=1,SUMIFS($H$3:$H$1000,$A$3:$A$1000,$A3,$C$3:$C$1000,"<>Demo")-P3,"↑"))
D4: =IF(AND($A4<>"",$A4=$A3),D3,"") | K4: =IF(AND($A4<>"",$A4=$A3),K3,"") | L4: =IF(AND($A4<>"",$A4=$A3),L3,"") | M4: =IF(AND($A4<>"",$A4=$A3),M3,"") | N4: =IF(H4="","",H4-G4) | O4: =IFERROR(N4/H4,"") | P4: =IF($A4="","",IF(COUNTIF($A$3:$A4,$A4)=1,SUMIF(cobranza!$B$3:$B$1000,$A4,cobranza!$D$3:$D$1000),"↑")) | Q4: =IF($A4="","",IF(COUNTIF($A$3:$A4,$A4)=1,SUMIFS($H$3:$H$1000,$A$3:$A$1000,$A4,$C$3:$C$1000,"<>Demo")-P4,"↑"))
D5: =IF(AND($A5<>"",$A5=$A4),D4,"") | K5: =IF(AND($A5<>"",$A5=$A4),K4,"") | L5: =IF(AND($A5<>"",$A5=$A4),L4,"") | M5: =IF(AND($A5<>"",$A5=$A4),M4,"") | N5: =IF(H5="","",H5-G5) | O5: =IFERROR(N5/H5,"") | P5: =IF($A5="","",IF(COUNTIF($A$3:$A5,$A5)=1,SUMIF(cobranza!$B$3:$B$1000,$A5,cobranza!$D$3:$D$1000),"↑")) | Q5: =IF($A5="","",IF(COUNTIF($A$3:$A5,$A5)=1,SUMIFS($H$3:$H$1000,$A$3:$A$1000,$A5,$C$3:$C$1000,"<>Demo")-P5,"↑"))
D6: =IF(AND($A6<>"",$A6=$A5),D5,"") | K6: =IF(AND($A6<>"",$A6=$A5),K5,"") | L6: =IF(AND($A6<>"",$A6=$A5),L5,"") | M6: =IF(AND($A6<>"",$A6=$A5),M5,"") | N6: =IF(H6="","",H6-G6) | O6: =IFERROR(N6/H6,"") | P6: =IF($A6="","",IF(COUNTIF($A$3:$A6,$A6)=1,SUMIF(cobranza!$B$3:$B$1000,$A6,cobranza!$D$3:$D$1000),"↑")) | Q6: =IF($A6="","",IF(COUNTIF($A$3:$A6,$A6)=1,SUMIFS($H$3:$H$1000,$A$3:$A$1000,$A6,$C$3:$C$1000,"<>Demo")-P6,"↑"))
D7: =IF(AND($A7<>"",$A7=$A6),D6,"") | K7: =IF(AND($A7<>"",$A7=$A6),K6,"") | L7: =IF(AND($A7<>"",$A7=$A6),L6,"") | M7: =IF(AND($A7<>"",$A7=$A6),M6,"") | N7: =IF(H7="","",H7-G7) | O7: =IFERROR(N7/H7,"") | P7: =IF($A7="","",IF(COUNTIF($A$3:$A7,$A7)=1,SUMIF(cobranza!$B$3:$B$1000,$A7,cobranza!$D$3:$D$1000),"↑")) | Q7: =IF($A7="","",IF(COUNTIF($A$3:$A7,$A7)=1,SUMIFS($H$3:$H$1000,$A$3:$A$1000,$A7,$C$3:$C$1000,"<>Demo")-P7,"↑"))
D8: =IF(AND($A8<>"",$A8=$A7),D7,"") | K8: =IF(AND($A8<>"",$A8=$A7),K7,"") | L8: =IF(AND($A8<>"",$A8=$A7),L7,"") | M8: =IF(AND($A8<>"",$A8=$A7),M7,"") | N8: =IF(H8="","",H8-G8) | O8: =IFERROR(N8/H8,"") | P8: =IF($A8="","",IF(COUNTIF($A$3:$A8,$A8)=1,SUMIF(cobranza!$B$3:$B$1000,$A8,cobranza!$D$3:$D$1000),"↑")) | Q8: =IF($A8="","",IF(COUNTIF($A$3:$A8,$A8)=1,SUMIFS($H$3:$H$1000,$A$3:$A$1000,$A8,$C$3:$C$1000,"<>Demo")-P8,"↑"))
D9: =IF(AND($A9<>"",$A9=$A8),D8,"") | K9: =IF(AND($A9<>"",$A9=$A8),K8,"") | L9: =IF(AND($A9<>"",$A9=$A8),L8,"") | M9: =IF(AND($A9<>"",$A9=$A8),M8,"") | N9: =IF(H9="","",H9-G9) | O9: =IFERROR(N9/H9,"") | P9: =IF($A9="","",IF(COUNTIF($A$3:$A9,$A9)=1,SUMIF(cobranza!$B$3:$B$1000,$A9,cobranza!$D$3:$D$1000),"↑")) | Q9: =IF($A9="","",IF(COUNTIF($A$3:$A9,$A9)=1,SUMIFS($H$3:$H$1000,$A$3:$A$1000,$A9,$C$3:$C$1000,"<>Demo")-P9,"↑"))
D10: =IF(AND($A10<>"",$A10=$A9),D9,"") | K10: =IF(AND($A10<>"",$A10=$A9),K9,"") | L10: =IF(AND($A10<>"",$A10=$A9),L9,"") | M10: =IF(AND($A10<>"",$A10=$A9),M9,"") | N10: =IF(H10="","",H10-G10) | O10: =IFERROR(N10/H10,"") | P10: =IF($A10="","",IF(COUNTIF($A$3:$A10,$A10)=1,SUMIF(cobranza!$B$3:$B$1000,$A10,cobranza!$D$3:$D$1000),"↑")) | Q10: =IF($A10="","",IF(COUNTIF($A$3:$A10,$A10)=1,SUMIFS($H$3:$H$1000,$A$3:$A$1000,$A10,$C$3:$C$1000,"<>Demo")-P10,"↑"))
D11: =IF(AND($A11<>"",$A11=$A10),D10,"") | K11: =IF(AND($A11<>"",$A11=$A10),K10,"") | L11: =IF(AND($A11<>"",$A11=$A10),L10,"") | M11: =IF(AND($A11<>"",$A11=$A10),M10,"") | N11: =IF(H11="","",H11-G11) | O11: =IFERROR(N11/H11,"") | P11: =IF($A11="","",IF(COUNTIF($A$3:$A11,$A11)=1,SUMIF(cobranza!$B$3:$B$1000,$A11,cobranza!$D$3:$D$1000),"↑")) | Q11: =IF($A11="","",IF(COUNTIF($A$3:$A11,$A11)=1,SUMIFS($H$3:$H$1000,$A$3:$A$1000,$A11,$C$3:$C$1000,"<>Demo")-P11,"↑"))
D12: =IF(AND($A12<>"",$A12=$A11),D11,"") | K12: =IF(AND($A12<>"",$A12=$A11),K11,"") | L12: =IF(AND($A12<>"",$A12=$A11),L11,"") | M12: =IF(AND($A12<>"",$A12=$A11),M11,"") | N12: =IF(H12="","",H12-G12) | O12: =IFERROR(N12/H12,"") | P12: =IF($A12="","",IF(COUNTIF($A$3:$A12,$A12)=1,SUMIF(cobranza!$B$3:$B$1000,$A12,cobranza!$D$3:$D$1000),"↑")) | Q12: =IF($A12="","",IF(COUNTIF($A$3:$A12,$A12)=1,SUMIFS($H$3:$H$1000,$A$3:$A$1000,$A12,$C$3:$C$1000,"<>Demo")-P12,"↑"))
D13: =IF(AND($A13<>"",$A13=$A12),D12,"") | K13: =IF(AND($A13<>"",$A13=$A12),K12,"") | L13: =IF(AND($A13<>"",$A13=$A12),L12,"") | M13: =IF(AND($A13<>"",$A13=$A12),M12,"") | N13: =IF(H13="","",H13-G13) | O13: =IFERROR(N13/H13,"") | P13: =IF($A13="","",IF(COUNTIF($A$3:$A13,$A13)=1,SUMIF(cobranza!$B$3:$B$1000,$A13,cobranza!$D$3:$D$1000),"↑")) | Q13: =IF($A13="","",IF(COUNTIF($A$3:$A13,$A13)=1,SUMIFS($H$3:$H$1000,$A$3:$A$1000,$A13,$C$3:$C$1000,"<>Demo")-P13,"↑"))
D14: =IF(AND($A14<>"",$A14=$A13),D13,"") | K14: =IF(AND($A14<>"",$A14=$A13),K13,"") | L14: =IF(AND($A14<>"",$A14=$A13),L13,"") | M14: =IF(AND($A14<>"",$A14=$A13),M13,"") | N14: =IF(H14="","",H14-G14) | O14: =IFERROR(N14/H14,"") | P14: =IF($A14="","",IF(COUNTIF($A$3:$A14,$A14)=1,SUMIF(cobranza!$B$3:$B$1000,$A14,cobranza!$D$3:$D$1000),"↑")) | Q14: =IF($A14="","",IF(COUNTIF($A$3:$A14,$A14)=1,SUMIFS($H$3:$H$1000,$A$3:$A$1000,$A14,$C$3:$C$1000,"<>Demo")-P14,"↑"))
... D301: =IF(AND($A301<>"",$A301=$A300),D300,"") | K301: =IF(AND($A301<>"",$A301=$A300),K300,"") | L301: =IF(AND($A301<>"",$A301=$A300),L300,"") | M301: =IF(AND($A301<>"",$A301=$A300),M300,"") | N301: =IF(H301="","",H301-G301) | O301: =IFERROR(N301/H301,"") | P301: =IF($A301="","",IF(COUNTIF($A$3:$A301,$A301)=1,SUMIF(cobranza!$B$3:$B$1000,$A301,cobranza!$D$3:$D$1000),"↑")) | Q301: =IF($A301="","",IF(COUNTIF($A$3:$A301,$A301)=1,SUMIFS($H$3:$H$1000,$A$3:$A$1000,$A301,$C$3:$C$1000,"<>Demo")-P301,"↑"))

Sheet cobranza
A1: folio_pago | B1: folio_venta | C1: fecha_pago | D1: monto | E1: metodo | F1: cliente_ref | G1: notas
A2: P-000 | B2: V-000 | C2: 20/04/2026 | D2: 100000 | E2: Transferencia | F2: EJEMPLO — Cliente Demostrativo | G2: Fila de ejemplo — no borrar

Sheet gastos
A1: folio_gasto | B1: fecha | C1: categoria | D1: subcategoria | E1: descripcion | F1: monto | G1: tipo | H1: proveedor | I1: notas
A2: G-000 | B2: 10/03/2026 | C2: Nomina | D2: Sueldo | E2: Sueldo mensual empleado operativo | F2: 15000 | G2: Fijo | H2: N/A | I2: Fila de ejemplo — no borrar

Sheet parametros
A1: parametro | B1: valor | C1: nota
A2: moneda_base | B2: MXN | C2: Moneda en que se capturan todos los importes.
A3: importes_incluyen_iva | C3: PENDIENTE — Escriba SI o NO. Critico: define si los reportes van con o sin IVA.
A4: tasa_iva | B4: 0.16 | C4: Tasa aplicable. Porcentaje: 16%, 16 o 0.16 valen lo mismo; un numero mayor que 1 se lee como por ciento.
A5: periodo_inicio | B5: 01/01/2026 | C5: Inicio del periodo a reportar.
A6: periodo_fin | B6: 31/12/2026 | C6: Fin del periodo a reportar.
A7: comision_base_default | C7: PENDIENTE — Escriba VENTA o UTILIDAD.
A8: dias_credito_default | C8: PENDIENTE — Dias de credito estandar que otorgan.
A9: provision_91_180 | B9: 0.25 | C9: % de la cartera de 91-180 dias que se estima incobrable. Porcentaje: 25%, 25 o 0.25; un numero mayor que 1 se lee como por ciento.
A10: provision_mas_180 | B10: 0.5 | C10: % de la cartera de mas de 180 dias que se estima incobrable. Porcentaje: 50%, 50 o 0.50; un numero mayor que 1 se lee como por ciento.
A11: tipo_cambio_usd | C11: Solo si compran en USD.
A12: nombre_cliente | C12: PENDIENTE — Nombre del cliente o empresa, tal como debe aparecer en la portada del reporte.
